TWMetro/__init__.py
TWMetro/client.py
TWMetro/api/__init__.py
TWMetro/api/transport.py
TWMetro/models/__init__.py
TWMetro/models/coordinates.py
TWMetro/models/metroline.py
TWMetro/models/metrostation.py
TWMetro/models/metrowarning.py
TWMetro/models/trainstatus.py
TWMetro/parsing/__init__.py
TWMetro/parsing/metrolines.py
TWMetro/parsing/metrostations.py
TWMetro/parsing/metrowarnings.py
TWMetro/parsing/trainstatuses.py
twmetro-0.0.2.dist-info/METADATA
twmetro-0.0.2.dist-info/WHEEL
twmetro-0.0.2.dist-info/top_level.txt
twmetro-0.0.2.dist-info/RECORD
