Metadata-Version: 2.4
Name: TWMetro
Version: 0.0.2
Summary: A simple package for reading data from the Tyne and Wear Metro API
Author-email: Lewis Foster <lewis@lewisfoster.foo>
Classifier: Programming Language :: Python :: 3
Classifier: Operating System :: OS Independent
Requires-Dist: requests>=2.32.5
